gym_fishing/__init__.py
gym_fishing/envs/__init__.py
gym_fishing/envs/age_structured.py
gym_fishing/envs/base_fishing_env.py
gym_fishing/envs/fishing_cts_env.py
gym_fishing/envs/fishing_env.py
gym_fishing/envs/fishing_model_error.py
gym_fishing/envs/fishing_tipping_env.py
gym_fishing/envs/growth_models.py
gym_fishing/envs/shared_env.py
gym_fishing/models/__init__.py
gym_fishing/models/policies.py
gym_fishing-0.1.0.dist-info/LICENSE.txt
gym_fishing-0.1.0.dist-info/METADATA
gym_fishing-0.1.0.dist-info/WHEEL
gym_fishing-0.1.0.dist-info/top_level.txt
gym_fishing-0.1.0.dist-info/RECORD
